cavoke_openapi_client/__init__.py
cavoke_openapi_client/api_client.py
cavoke_openapi_client/configuration.py
cavoke_openapi_client/exceptions.py
cavoke_openapi_client/model_utils.py
cavoke_openapi_client/rest.py
cavoke_openapi_client/api/__init__.py
cavoke_openapi_client/api/default_api.py
cavoke_openapi_client/apis/__init__.py
cavoke_openapi_client/model/__init__.py
cavoke_openapi_client/model/error.py
cavoke_openapi_client/model/game_info.py
cavoke_openapi_client/model/game_move.py
cavoke_openapi_client/model/game_state.py
cavoke_openapi_client/model/game_statistics.py
cavoke_openapi_client/model/invite_code.py
cavoke_openapi_client/model/occupied_positions.py
cavoke_openapi_client/model/player.py
cavoke_openapi_client/model/room_info.py
cavoke_openapi_client/model/session_creation_request.py
cavoke_openapi_client/model/session_info.py
cavoke_openapi_client/model/user.py
cavoke_openapi_client/model/user_game_statistics.py
cavoke_openapi_client/model/user_statistics.py
cavoke_openapi_client/model/validation_result.py
cavoke_openapi_client/models/__init__.py
cavoke_openapi_client-1.0.3.dist-info/METADATA
cavoke_openapi_client-1.0.3.dist-info/WHEEL
cavoke_openapi_client-1.0.3.dist-info/top_level.txt
cavoke_openapi_client-1.0.3.dist-info/RECORD
