Metadata-Version: 2.1
Name: cavoke-openapi-client
Version: 1.0.3
Summary: Cavoke
Home-page: 
Author: OpenAPI Generator community
Author-email: team@openapitools.org
Keywords: OpenAPI,OpenAPI-Generator,Cavoke
Requires-Python: >=3.6
Requires-Dist: urllib3 (>=1.25.3)
Requires-Dist: python-dateutil
